fine_python_flake8/__init__.py
fine_python_flake8/action.py
fine_python_flake8/py.typed
fine_python_flake8-0.2.1.dist-info/METADATA
fine_python_flake8-0.2.1.dist-info/WHEEL
fine_python_flake8-0.2.1.dist-info/top_level.txt
fine_python_flake8-0.2.1.dist-info/RECORD
