Metadata-Version: 2.4
Name: fine_python_flake8
Version: 0.2.1
Author-email: Vladyslav Hnatiuk <aders1234@gmail.com>
Requires-Python: <3.14,>=3.11
Requires-Dist: finecode_extension_api==0.3.*
Requires-Dist: fine_python_ast==0.2.*
Requires-Dist: types-flake8<8.0.0.0,>=7.1.0.20241020
Requires-Dist: flake8<8.0.0,>=7.1.2
